libexploit/__init__.py
libexploit/io/__init__.py
libexploit/io/stdout.py
libexploit/offsets/__init__.py
libexploit/offsets/hex.py
libexploit/payloads/__init__.py
libexploit/payloads/validation.py
libexploit/targets/__init__.py
libexploit/targets/network.py
libexploit-0.0.3.dist-info/LICENSE
libexploit-0.0.3.dist-info/METADATA
libexploit-0.0.3.dist-info/WHEEL
libexploit-0.0.3.dist-info/entry_points.txt
libexploit-0.0.3.dist-info/top_level.txt
libexploit-0.0.3.dist-info/RECORD
