Metadata-Version: 2.1
Name: libexploit
Version: 0.0.3
Summary: Python exploit development utility library
Home-page: https://github.com/kkirsche/libexploit
Author: Kevin Kirsche
License: UNKNOWN
Project-URL: Bug Reports, https://github.com/kkirsche/libexploit/issues
Project-URL: Source, https://github.com/kkirsche/libexploit
Keywords: exploit pentest
Platform: UNKNOWN
Classifier: Development Status :: 3 - Alpha
Classifier: Intended Audience :: Developers
Classifier: Programming Language :: Python :: 2
Classifier: Programming Language :: Python :: 2.7
Classifier: Programming Language :: Python :: 3
Classifier: Programming Language :: Python :: 3.4
Classifier: Programming Language :: Python :: 3.5
Classifier: Programming Language :: Python :: 3.6
Requires-Dist: colorlog
Provides-Extra: dev
Provides-Extra: test
